odoo/addons/energy_selfconsumption/README.md
odoo/addons/energy_selfconsumption/README.rst
odoo/addons/energy_selfconsumption/__init__.py
odoo/addons/energy_selfconsumption/__manifest__.py
odoo/addons/energy_selfconsumption/config.py
odoo/addons/energy_selfconsumption/components/__init__.py
odoo/addons/energy_selfconsumption/components/contract_utils.py
odoo/addons/energy_selfconsumption/controllers/__init__.py
odoo/addons/energy_selfconsumption/controllers/controllers.py
odoo/addons/energy_selfconsumption/controllers/inscriptions_form_controllers.py
odoo/addons/energy_selfconsumption/data/contract_line_qty_formula_data.xml
odoo/addons/energy_selfconsumption/data/contract_template_data.xml
odoo/addons/energy_selfconsumption/data/custom_paper_format_views.xml
odoo/addons/energy_selfconsumption/data/ir_attachment_data.xml
odoo/addons/energy_selfconsumption/data/ir_cron.xml
odoo/addons/energy_selfconsumption/data/ir_sequence_data.xml
odoo/addons/energy_selfconsumption/data/mail_template.xml
odoo/addons/energy_selfconsumption/data/product_data.xml
odoo/addons/energy_selfconsumption/data/project_type_data.xml
odoo/addons/energy_selfconsumption/data/service_available_data.xml
odoo/addons/energy_selfconsumption/demo/energy_selfconsumption_demo.xml
odoo/addons/energy_selfconsumption/i18n/ca_ES.po
odoo/addons/energy_selfconsumption/i18n/energy_selfconsumption.pot
odoo/addons/energy_selfconsumption/i18n/es.po
odoo/addons/energy_selfconsumption/i18n/eu_ES.po
odoo/addons/energy_selfconsumption/i18n_extra/ca_ES.po
odoo/addons/energy_selfconsumption/i18n_extra/es.po
odoo/addons/energy_selfconsumption/i18n_extra/eu_ES.po
odoo/addons/energy_selfconsumption/migrations/14.0.3.4.0/post-migration.py
odoo/addons/energy_selfconsumption/migrations/16.0.0.1.6/post-migration.py
odoo/addons/energy_selfconsumption/migrations/16.0.0.1.6/pre-migration.py
odoo/addons/energy_selfconsumption/migrations/16.0.0.3.0/post-migration.py
odoo_addon_energy_selfconsumption-16.0.0.5.14.dist-info/METADATA
odoo_addon_energy_selfconsumption-16.0.0.5.14.dist-info/WHEEL
odoo_addon_energy_selfconsumption-16.0.0.5.14.dist-info/top_level.txt
odoo_addon_energy_selfconsumption-16.0.0.5.14.dist-info/RECORD
