Metadata-Version: 2.1
Name: odoo-addon-energy_selfconsumption
Version: 16.0.0.5.14
Requires-Python: >=3.10
Requires-Dist: numpy>=1.24.4
Requires-Dist: odoo-addon-contract>=16.0dev,<16.1dev
Requires-Dist: odoo-addon-contract_mandate>=16.0dev,<16.1dev
Requires-Dist: odoo-addon-contract_queue_job>=16.0dev,<16.1dev
Requires-Dist: odoo-addon-contract_variable_quantity>=16.0dev,<16.1dev
Requires-Dist: odoo-addon-energy_communities>=16.0dev,<16.1dev
Requires-Dist: odoo-addon-energy_communities_cooperator>=16.0dev,<16.1dev
Requires-Dist: odoo-addon-energy_communities_service_invoicing>=16.0dev,<16.1dev
Requires-Dist: odoo-addon-energy_project>=16.0dev,<16.1dev
Requires-Dist: odoo-addon-report_csv>=16.0dev,<16.1dev
Requires-Dist: odoo-addon-web_m2x_options>=16.0dev,<16.1dev
Requires-Dist: odoo>=16.0a,<16.1dev
Requires-Dist: openupgradelib>=3.12.0
Requires-Dist: pandas>=2.0.3
Summary: Comprehensive management of energy self-consumption projects and communities
Home-page: https://git.coopdevs.org/coopdevs/comunitats-energetiques/odoo-ce
License: AGPL-3
Author: Som IT SCCL & Som Energia SCCL
Classifier: Programming Language :: Python
Classifier: Framework :: Odoo
Classifier: Framework :: Odoo :: 16.0
Classifier: License :: OSI Approved :: GNU Affero General Public License v3
Classifier: Development Status :: 5 - Production/Stable
